coomatrix/__init__.py
coomatrix/coomatrix.py
coomatrix-0.0.1.dist-info/LICENSE
coomatrix-0.0.1.dist-info/METADATA
coomatrix-0.0.1.dist-info/WHEEL
coomatrix-0.0.1.dist-info/top_level.txt
coomatrix-0.0.1.dist-info/RECORD
