Metadata-Version: 2.1
Name: coomatrix
Version: 0.0.1
Summary: This package calculates the Co-occurence matrix.
Home-page: https://github.com/calculatecooccurencematrix/coomatrix
Author: Gaurav Singh
Author-email: gs8763076@gmail.com
License: UNKNOWN
Platform: UNKNOWN
Classifier: Programming Language :: Python :: 3.6
Classifier: License :: OSI Approved :: GNU General Public License v3 (GPLv3)
Requires-Dist: tqdm (>=4.23.4)
Requires-Dist: numpy (>=1.16.2)
